confhub/__init__.py
confhub/__main__.py
confhub/__meta__.py
confhub/builder.py
confhub/commands.py
confhub/console.py
confhub/reader.py
confhub/setup_logger.py
confhub/templates.py
confhub/core/__init__.py
confhub/core/block.py
confhub/core/error.py
confhub/core/fields.py
confhub/core/parsing.py
confhub/core/types.py
confhub/utils/__init__.py
confhub/utils/__inspect.py
confhub/utils/__models.py
confhub/utils/gitignore.py
confhub-0.1.0.7a0.dist-info/METADATA
confhub-0.1.0.7a0.dist-info/WHEEL
confhub-0.1.0.7a0.dist-info/entry_points.txt
confhub-0.1.0.7a0.dist-info/licenses/LICENSE
confhub-0.1.0.7a0.dist-info/RECORD
