Metadata-Version: 2.3
Name: confhub
Version: 0.1.0.7a0
Summary: Configuration add-on to Dynaconf
Project-URL: Repository, https://github.com/morington/confhub/
Author-email: Adam Morington <morington.mail@gmail.com>
License-Expression: MIT
License-File: LICENSE
Keywords: cfg,confhub,config,configuration,dynaconf,setting,settings
Classifier: Development Status :: 3 - Alpha
Classifier: Intended Audience :: Developers
Classifier: Intended Audience :: System Administrators
Classifier: License :: OSI Approved :: MIT License
Classifier: Programming Language :: Python :: 3.11
Classifier: Programming Language :: Python :: Implementation :: PyPy
Classifier: Topic :: Software Development :: Libraries :: Python Modules
Classifier: Topic :: System :: Distributed Computing
Classifier: Topic :: Utilities
Classifier: Typing :: Typed
Requires-Python: >=3.11
Requires-Dist: pytest>=8.1.1
Requires-Dist: pyyaml>=6.0.1
Requires-Dist: structlog>=24.1.0
Requires-Dist: yarl>=1.9.4
